codepromptforge/__init__.py
codepromptforge/assistant/web_assistant/static/style.css
codepromptforge/assistant/web_assistant/static/terminal.css
codepromptforge/assistant/web_assistant/templates/index.html
codepromptforge/core/__init__.py
codepromptforge/core/cli.py
codepromptforge/core/main.py
codepromptforge/core/prompt.py
codepromptforge-1.1.0.dist-info/METADATA
codepromptforge-1.1.0.dist-info/WHEEL
codepromptforge-1.1.0.dist-info/entry_points.txt
codepromptforge-1.1.0.dist-info/top_level.txt
codepromptforge-1.1.0.dist-info/RECORD
