Metadata-Version: 2.2
Name: codepromptforge
Version: 1.1.0
Summary: A tool to combine code files into a single prompt
Home-page: https://github.com/RobinsonGarcia/CodePromptForge
Author: RG
Author-email: rlsgarcia@icloud.com
Classifier: Programming Language :: Python :: 3
Classifier: License :: OSI Approved :: MIT License
Classifier: Operating System :: OS Independent
Requires-Python: >=3.7
Requires-Dist: pytest
Requires-Dist: pydantic
Requires-Dist: langchain
Requires-Dist: pathspec
Requires-Dist: langchain_community
Provides-Extra: assistant
Requires-Dist: langchain_ollama; extra == "assistant"
Requires-Dist: langgraph; extra == "assistant"
Requires-Dist: ollama; extra == "assistant"
Requires-Dist: duckduckgo-search; extra == "assistant"
Requires-Dist: flask; extra == "assistant"
Dynamic: author
Dynamic: author-email
Dynamic: classifier
Dynamic: description
Dynamic: description-content-type
Dynamic: home-page
Dynamic: provides-extra
Dynamic: requires-dist
Dynamic: requires-python
Dynamic: summary
